freedom_pay/__init__.py
freedom_pay/service.py
freedom_pay/utils.py
freedom_pay-0.0.4.dist-info/LICENSE
freedom_pay-0.0.4.dist-info/METADATA
freedom_pay-0.0.4.dist-info/WHEEL
freedom_pay-0.0.4.dist-info/top_level.txt
freedom_pay-0.0.4.dist-info/RECORD
